furhat_ws_api/__init__.py
furhat_ws_api/async_furhat_client.py
furhat_ws_api/events.py
furhat_ws_api/furhat_client.py
furhat_ws_api-0.1.2.dist-info/METADATA
furhat_ws_api-0.1.2.dist-info/WHEEL
furhat_ws_api-0.1.2.dist-info/entry_points.txt
furhat_ws_api-0.1.2.dist-info/RECORD
