Metadata-Version: 2.4
Name: furhat_ws_api
Version: 0.1.2
Summary: A Python client for the Furhat WebSocket API.
Project-URL: Homepage, https://docs.furhat.io/
Author-email: Your Name <you@example.com>
Keywords: api,client,furhat,robotics,websocket
Classifier: License :: OSI Approved :: MIT License
Classifier: Operating System :: OS Independent
Classifier: Programming Language :: Python :: 3
Requires-Python: >=3.9
Requires-Dist: asyncio
Requires-Dist: websockets
